poetry_dlee/__init__.py
poetry_dlee-0.1.0.dist-info/METADATA
poetry_dlee-0.1.0.dist-info/WHEEL
poetry_dlee-0.1.0.dist-info/RECORD
