Metadata-Version: 2.1
Name: poetry-dlee
Version: 0.1.0
Summary: 
Author: insightintosoftware
Author-email: insightintosoftware@gmail.com
Requires-Python: >=3.11,<4.0
Classifier: Programming Language :: Python :: 3
Classifier: Programming Language :: Python :: 3.11
Classifier: Programming Language :: Python :: 3.12
Requires-Dist: pydantic (>=2.7.4,<3.0.0)
